{
    "_id": "MvWzD22qi92ZF6q0",
    "img": "systems/pf2e/icons/default-icons/npc.svg",
    "items": [
        {
            "_id": "sh7iK8xqS8cHsays",
            "img": "systems/pf2e/icons/actions/TwoActions.webp",
            "name": "Javelin Barrage",
            "sort": 100000,
            "system": {
                "actionType": {
                    "value": "action"
                },
                "actions": {
                    "value": 2
                },
                "category": "defensive",
                "description": {
                    "value": "<p>The xulgaths draw javelins and launch a coordinated barrage at range. This barrage is a @Template[type:burst|distance:10] within 30 feet that deals @Damage[4d8[piercing]|options:area-damage] damage (@Check[reflex|dc:30|basic|options:area-effect] save). When the cavalry is reduced to 2 segments, this area decreases to a @Template[type:burst|distance:5].</p>"
                },
                "publication": {
                    "license": "OGL",
                    "remaster": false,
                    "title": ""
                },
                "rules": [],
                "slug": null,
                "traits": {
                    "value": []
                }
            },
            "type": "action"
        },
        {
            "_id": "9jcmqB6dSzdXSCNa",
            "img": "systems/pf2e/icons/actions/Passive.webp",
            "name": "Stench",
            "sort": 200000,
            "system": {
                "actionType": {
                    "value": "passive"
                },
                "actions": {
                    "value": null
                },
                "category": "defensive",
                "description": {
                    "value": "<p>30 feet @Check[fortitude|dc:33]</p><hr /><p>@Localize[PF2E.NPC.Abilities.Glossary.Stench]</p>"
                },
                "publication": {
                    "license": "ORC",
                    "remaster": true,
                    "title": "Pathfinder Monster Core"
                },
                "rules": [
                    {
                        "key": "Aura",
                        "radius": 30,
                        "slug": "stench",
                        "traits": [
                            "olfactory"
                        ]
                    }
                ],
                "slug": "stench",
                "traits": {
                    "value": [
                        "aura",
                        "olfactory"
                    ]
                }
            },
            "type": "action"
        },
        {
            "_id": "icFtpyk3vKrnSxKV",
            "img": "systems/pf2e/icons/actions/Passive.webp",
            "name": "Troop Defenses",
            "sort": 300000,
            "system": {
                "actionType": {
                    "value": "passive"
                },
                "actions": {
                    "value": null
                },
                "category": "defensive",
                "description": {
                    "value": "<p><strong>HP</strong> 240 (4 segments); <strong>Thresholds</strong> 160 (3 segments), 80 (2 segments)</p>\n<p>@Localize[PF2E.NPC.Abilities.Glossary.TroopDefenses]</p>"
                },
                "publication": {
                    "license": "ORC",
                    "remaster": true,
                    "title": "Pathfinder NPC Core"
                },
                "rules": [],
                "slug": "troop-defenses",
                "traits": {
                    "value": []
                }
            },
            "type": "action"
        },
        {
            "_id": "i5jWmQ8e6h6E4QoP",
            "img": "systems/pf2e/icons/actions/Passive.webp",
            "name": "Troop Movement",
            "sort": 400000,
            "system": {
                "actionType": {
                    "value": "passive"
                },
                "actions": {
                    "value": null
                },
                "category": "defensive",
                "description": {
                    "value": "<p>@Localize[PF2E.NPC.Abilities.Glossary.TroopMovement]</p>"
                },
                "publication": {
                    "license": "ORC",
                    "remaster": true,
                    "title": "Pathfinder NPC Core"
                },
                "rules": [],
                "slug": "troop-movement",
                "traits": {
                    "value": []
                }
            },
            "type": "action"
        },
        {
            "_id": "EyzM8IsGsCsC2eQu",
            "folder": "Dlh3fyXZTRsjSMCF",
            "img": "systems/pf2e/icons/actions/Passive.webp",
            "name": "Mounted Troop",
            "sort": 500000,
            "system": {
                "actionType": {
                    "value": "passive"
                },
                "actions": {
                    "value": null
                },
                "category": "offensive",
                "description": {
                    "value": "<p>Effects that target only animals or only humanoids may not work on the valkyrie tempest, subject to the GM's discretion.</p>"
                },
                "publication": {
                    "license": "ORC",
                    "remaster": true,
                    "title": "Pathfinder Battlecry!"
                },
                "rules": [],
                "slug": "valkyrie-tempest-mounted-troop",
                "traits": {
                    "value": []
                }
            },
            "type": "action"
        },
        {
            "_id": "OA4p28bD8vELnas7",
            "img": "systems/pf2e/icons/actions/OneThreeActions.webp",
            "name": "Spears, Teeth, and Horns",
            "sort": 600000,
            "system": {
                "actionType": {
                    "value": "action"
                },
                "actions": {
                    "value": 1
                },
                "category": "offensive",
                "description": {
                    "value": "<p><span class=\"action-glyph\">1</span> to <span class=\"action-glyph\">3</span></p>\n<p><strong>Frequency</strong> once per round</p><hr /><p><strong>Effect</strong> The cavalry makes a coordinated melee attack against each enemy in @Template[type:emanation|distance:10], with a @Check[reflex|dc:30|basic|options:area-effect] save. The damage dealt depends on the number of actions.</p>\n<p><span class=\"action-glyph\">1</span> @Damage[(2d6+2)[piercing]|options:area-damage] damage</p>\n<p><span class=\"action-glyph\">2</span> @Damage[(4d6+10)[piercing]|options:area-damage] damage</p>\n<p><span class=\"action-glyph\">3</span> @Damage[(5d6+15)[piercing]|options:area-damage] damage</p>"
                },
                "frequency": {
                    "max": 1,
                    "per": "round"
                },
                "publication": {
                    "license": "OGL",
                    "remaster": false,
                    "title": ""
                },
                "rules": [],
                "slug": null,
                "traits": {
                    "value": []
                }
            },
            "type": "action"
        },
        {
            "_id": "tFEpets9UJimpctg",
            "img": "systems/pf2e/icons/actions/ThreeActions.webp",
            "name": "Trample",
            "sort": 700000,
            "system": {
                "actionType": {
                    "value": "action"
                },
                "actions": {
                    "value": 3
                },
                "category": "offensive",
                "description": {
                    "value": "<p>Large or smaller, @Damage[(2d6+2)[bludgeoning]], @Check[reflex|dc:30|basic]</p>\n<hr />\n<p>@Localize[PF2E.NPC.Abilities.Glossary.Trample]</p>"
                },
                "publication": {
                    "license": "ORC",
                    "remaster": true,
                    "title": "Pathfinder Monster Core"
                },
                "rules": [],
                "slug": "trample",
                "traits": {
                    "value": []
                }
            },
            "type": "action"
        },
        {
            "_id": "lC8aWPfSCuRLOqnS",
            "img": "systems/pf2e/icons/default-icons/lore.svg",
            "name": "Dinosaur Lore",
            "sort": 800000,
            "system": {
                "description": {
                    "value": ""
                },
                "mod": {
                    "value": 24
                },
                "proficient": {
                    "value": 0
                },
                "publication": {
                    "license": "OGL",
                    "remaster": false,
                    "title": ""
                },
                "rules": [],
                "slug": null,
                "traits": {}
            },
            "type": "lore"
        }
    ],
    "name": "Xulgath Dinosaur Cavalry",
    "system": {
        "abilities": {
            "cha": {
                "mod": 3
            },
            "con": {
                "mod": 5
            },
            "dex": {
                "mod": 2
            },
            "int": {
                "mod": -1
            },
            "str": {
                "mod": 8
            },
            "wis": {
                "mod": 4
            }
        },
        "attributes": {
            "ac": {
                "details": "",
                "value": 33
            },
            "allSaves": {
                "value": ""
            },
            "hp": {
                "details": "(4 segments); Thresholds 160 (3 segments), 80 (2 segments)",
                "max": 240,
                "temp": 0,
                "value": 240
            },
            "speed": {
                "details": "troop movement",
                "otherSpeeds": [],
                "value": 30
            },
            "weaknesses": [
                {
                    "exceptions": [],
                    "type": "area-damage",
                    "value": 15
                },
                {
                    "exceptions": [],
                    "type": "splash-damage",
                    "value": 15
                }
            ]
        },
        "details": {
            "blurb": "",
            "languages": {
                "details": "",
                "value": [
                    "draconic",
                    "sakvroth"
                ]
            },
            "level": {
                "value": 13
            },
            "privateNotes": "",
            "publicNotes": "<p>Xulgaths have been breeding and training dinosaurs for millennia, and the bonds between them are as familiar and strong as that between any other humanoid and their domesticated companion of choice. While most of the creatures are used primarily as beasts of burden, elite xulgath soldiers known as roughriders train the most vicious and aggressive dinosaurs from numerous species to serve as vicious and terrifying mounts, capable of punching through defensive lines and smashing fortifications to splinters as easily as they scatter enemy soldiers.</p>",
            "publication": {
                "license": "ORC",
                "remaster": true,
                "title": "Pathfinder Battlecry!"
            }
        },
        "initiative": {
            "statistic": "perception"
        },
        "perception": {
            "details": "",
            "mod": 23,
            "senses": [
                {
                    "type": "low-light-vision"
                },
                {
                    "acuity": "imprecise",
                    "range": 30,
                    "type": "scent"
                }
            ]
        },
        "resources": {},
        "saves": {
            "fortitude": {
                "saveDetail": "",
                "value": 29
            },
            "reflex": {
                "saveDetail": "",
                "value": 20
            },
            "will": {
                "saveDetail": "",
                "value": 23
            }
        },
        "skills": {
            "athletics": {
                "base": 27
            },
            "intimidation": {
                "base": 24
            }
        },
        "traits": {
            "rarity": "common",
            "size": {
                "value": "grg"
            },
            "value": [
                "animal",
                "dinosaur",
                "humanoid",
                "troop",
                "xulgath"
            ]
        }
    },
    "type": "npc"
}
