{
    "_id": "qZK8Jbg59oIpUS7W",
    "folder": "T3l4WZ3e6Om1Xaiq",
    "img": "systems/sf2e/icons/default-icons/feats-sf2e.webp",
    "name": "Drift Hop",
    "system": {
        "actionType": {
            "value": "action"
        },
        "actions": {
            "value": 1
        },
        "category": "ancestry",
        "description": {
            "value": "<p><strong>Frequency</strong> once per day</p><hr /><p>You travel across the battlefield via the Drift. You teleport up to a distance equal to your Speed within your line of sight. If you're in the Drift, the distance you can teleport is doubled.</p>"
        },
        "frequency": {
            "max": 1,
            "per": "day"
        },
        "level": {
            "value": 5
        },
        "prerequisites": {
            "value": []
        },
        "publication": {
            "license": "ORC",
            "remaster": true,
            "title": "Starfinder Player Core"
        },
        "rules": [],
        "subfeatures": {
            "proficiencies": {},
            "senses": {},
            "suppressedFeatures": []
        },
        "traits": {
            "rarity": "common",
            "value": [
                "prismeni",
                "teleportation"
            ]
        }
    },
    "type": "feat"
}
