{
    "_id": "YS3PKzT45AcAy9qj",
    "img": "systems/sf2e/icons/default-icons/npc.svg",
    "items": [
        {
            "_id": "HDwOm4f4xPT9o1RF",
            "img": "systems/sf2e/icons/default-icons/melee.svg",
            "name": "Lash",
            "sort": 100000,
            "system": {
                "action": "strike",
                "area": null,
                "attackEffects": {
                    "value": []
                },
                "bonus": {
                    "value": 14
                },
                "damageRolls": {
                    "YRJn7NY8AcrrEJRc": {
                        "damage": "2d6+4",
                        "damageType": "bludgeoning"
                    }
                },
                "description": {
                    "value": ""
                },
                "publication": {
                    "license": "OGL",
                    "remaster": false,
                    "title": ""
                },
                "range": null,
                "rules": [],
                "slug": null,
                "traits": {
                    "value": [
                        "reach-15"
                    ]
                }
            },
            "type": "melee"
        },
        {
            "_id": "if3IVJEl7OmynnWZ",
            "img": "systems/sf2e/icons/default-icons/melee.svg",
            "name": "Spores",
            "sort": 200000,
            "system": {
                "action": "strike",
                "area": null,
                "attackEffects": {
                    "value": []
                },
                "bonus": {
                    "value": 14
                },
                "damageRolls": {
                    "TNqWdKR92ROkVR6z": {
                        "damage": "2d4+4",
                        "damageType": "poison"
                    }
                },
                "description": {
                    "value": ""
                },
                "publication": {
                    "license": "OGL",
                    "remaster": false,
                    "title": ""
                },
                "range": {
                    "increment": 30,
                    "max": null
                },
                "rules": [],
                "slug": null,
                "traits": {
                    "value": [
                        "brutal"
                    ]
                }
            },
            "type": "melee"
        },
        {
            "_id": "fmdL1CD5WWQITDHY",
            "img": "systems/sf2e/icons/actions/Passive.webp",
            "name": "Mycelium Network",
            "sort": 300000,
            "system": {
                "actionType": {
                    "value": "passive"
                },
                "actions": {
                    "value": null
                },
                "category": "interaction",
                "description": {
                    "value": "<p>Psychic fungi are connected to a network of psychic filaments bonding all psychic fungi from the same colony. This network grants the harvester the ability to detect creatures capable of thought within 30 feet of a bonded psychic fungus up to 1,000 feet away as an imprecise sense.</p>"
                },
                "publication": {
                    "license": "OGL",
                    "remaster": false,
                    "title": ""
                },
                "rules": [],
                "slug": null,
                "traits": {
                    "value": []
                }
            },
            "type": "action"
        },
        {
            "_id": "ZdQCNmA8Cmv5ac9q",
            "img": "systems/sf2e/icons/actions/Reaction.webp",
            "name": "Release Spores",
            "sort": 400000,
            "system": {
                "actionType": {
                    "value": "reaction"
                },
                "actions": {
                    "value": null
                },
                "category": "defensive",
                "description": {
                    "value": "<p><strong>Trigger</strong> The harvester is reduced to 0 Hit Points</p><hr /><p><strong>Effect</strong> The harvester releases a cloud of spores in a @Template[type:burst|distance:10] centered on a corner of its own space that lasts for 1 round. Each creature that's in the cloud or enters it is exposed to befuddling spores. If this reaction was triggered by damage from a melee attack, the triggering creature uses the outcome one degree of success worse than the result of its roll for its Fortitude save (two degrees worse if it was a jaws Strike or other Strike with the creature's mouth).</p>"
                },
                "publication": {
                    "license": "OGL",
                    "remaster": false,
                    "title": ""
                },
                "rules": [],
                "slug": null,
                "traits": {
                    "value": []
                }
            },
            "type": "action"
        },
        {
            "_id": "Q1pJ9vSYbZJYeohd",
            "img": "systems/sf2e/icons/actions/Passive.webp",
            "name": "Befuddling Spores",
            "sort": 500000,
            "system": {
                "actionType": {
                    "value": "passive"
                },
                "actions": {
                    "value": null
                },
                "category": "offensive",
                "description": {
                    "value": "<p>Plants and fungi are immune</p>\n<p><strong>Saving Throw</strong> @Check[fortitude|dc:21]</p>\n<p><strong>Maximum Duration</strong> 6 rounds</p>\n<p><strong>Stage 1</strong> @UUID[Compendium.sf2e.conditions.Item.Stupefied]{Stupefied 1} (1 round)</p>\n<p><strong>Stage 2</strong> @UUID[Compendium.sf2e.conditions.Item.Stupefied]{Stupefied 2} (1 round)</p>\n<p><strong>Stage 3</strong> @UUID[Compendium.sf2e.conditions.Item.Slowed]{Slowed 1} and @UUID[Compendium.sf2e.conditions.Item.Stupefied]{Stupefied 3} (1 round)</p>\n<p><strong>Stage 4</strong> @UUID[Compendium.sf2e.conditions.Item.Paralyzed] and @UUID[Compendium.sf2e.conditions.Item.Stupefied]{Stupefied 4} (1 round)</p>"
                },
                "publication": {
                    "license": "OGL",
                    "remaster": false,
                    "title": ""
                },
                "rules": [],
                "slug": null,
                "traits": {
                    "value": [
                        "poison"
                    ]
                }
            },
            "type": "action"
        },
        {
            "_id": "nwLCmCiSIvoxRQu9",
            "img": "systems/sf2e/icons/actions/OneAction.webp",
            "name": "Drain Brain",
            "sort": 600000,
            "system": {
                "actionType": {
                    "value": "action"
                },
                "actions": {
                    "value": 1
                },
                "category": "offensive",
                "description": {
                    "value": "<p>The elder psychic fungus consumes the fluids and psychic essences from the brain of a creature within 10 feet that has been dead for no more than 1 minute. The elder psychic fungus regains the use of their highest-ranked spent innate spell. The creature is considered to have died due to a death effect.</p>"
                },
                "publication": {
                    "license": "OGL",
                    "remaster": false,
                    "title": ""
                },
                "rules": [],
                "slug": null,
                "traits": {
                    "value": [
                        "manipulate"
                    ]
                }
            },
            "type": "action"
        },
        {
            "_id": "pKa8pWaDXjw6sf9G",
            "img": "systems/sf2e/icons/default-icons/lore.svg",
            "name": "Lore (all subcategories of all creatures trained in Lore skills within 1 mile)",
            "sort": 700000,
            "system": {
                "description": {
                    "value": ""
                },
                "mod": {
                    "value": 13
                },
                "proficient": {
                    "value": 0
                },
                "publication": {
                    "license": "OGL",
                    "remaster": false,
                    "title": ""
                },
                "rules": [],
                "slug": null,
                "traits": {}
            },
            "type": "lore"
        }
    ],
    "name": "Elder Psychic Fungus",
    "system": {
        "abilities": {
            "cha": {
                "mod": 0
            },
            "con": {
                "mod": 4
            },
            "dex": {
                "mod": 0
            },
            "int": {
                "mod": 5
            },
            "str": {
                "mod": 4
            },
            "wis": {
                "mod": 1
            }
        },
        "attributes": {
            "ac": {
                "details": "",
                "value": 18
            },
            "allSaves": {
                "value": ""
            },
            "hp": {
                "details": "",
                "max": 72,
                "temp": 0,
                "value": 72
            },
            "speed": {
                "otherSpeeds": [],
                "value": 10
            }
        },
        "details": {
            "blurb": "",
            "languages": {
                "details": "Can't speak, Telepathy 120 feet",
                "value": [
                    "common"
                ]
            },
            "level": {
                "value": 4
            },
            "privateNotes": "",
            "publicNotes": "",
            "publication": {
                "license": "ORC",
                "remaster": true,
                "title": "Starfinder Alien Core"
            }
        },
        "initiative": {
            "statistic": "perception"
        },
        "perception": {
            "details": "darkvision, mycelium network",
            "mod": 13,
            "senses": []
        },
        "resources": {},
        "saves": {
            "fortitude": {
                "saveDetail": "",
                "value": 12
            },
            "reflex": {
                "saveDetail": "",
                "value": 8
            },
            "will": {
                "saveDetail": "",
                "value": 11
            }
        },
        "skills": {
            "athletics": {
                "base": 12
            },
            "society": {
                "base": 11
            }
        },
        "traits": {
            "rarity": "common",
            "size": {
                "value": "lg"
            },
            "value": [
                "fungus"
            ]
        }
    },
    "type": "npc"
}
