{
    "_id": "8FyWTto9DlAH3l7e",
    "img": "systems/sf2e/icons/default-icons/npc.svg",
    "items": [
        {
            "_id": "Tz40XsThj2Ou0XlF",
            "img": "systems/sf2e/icons/default-icons/spellcastingEntry.svg",
            "name": "Arcane Innate Spells",
            "sort": 100000,
            "system": {
                "autoHeightenLevel": {
                    "value": 2
                },
                "description": {
                    "value": ""
                },
                "prepared": {
                    "value": "innate"
                },
                "proficiency": {
                    "value": 1
                },
                "publication": {
                    "license": "OGL",
                    "remaster": false,
                    "title": ""
                },
                "rules": [],
                "slots": {},
                "slug": null,
                "spelldc": {
                    "dc": 18,
                    "value": 10
                },
                "tradition": {
                    "value": "arcane"
                },
                "traits": {}
            },
            "type": "spellcastingEntry"
        },
        {
            "_id": "3nCga39nOpHfRhxx",
            "folder": "KGETkFaB5r8FyUND",
            "img": "systems/sf2e/icons/abilities/blue-comet.webp",
            "name": "Inject Nanobots",
            "sort": 200000,
            "system": {
                "area": null,
                "cost": {
                    "value": ""
                },
                "counteraction": false,
                "damage": {
                    "Xdnfrdvjfv7q0CPF": {
                        "applyMod": false,
                        "category": null,
                        "formula": "4d6",
                        "kinds": [
                            "damage"
                        ],
                        "materials": [],
                        "type": "acid"
                    }
                },
                "defense": null,
                "description": {
                    "value": "<p>You inject magical nanobots into a creature. Make a melee spell attack roll. On a hit, the target takes 4d6 acid damage. On a critical hit, the target takes double damage and becomes @UUID[Compendium.sf2e.conditions.Item.Confused] for 1 round as nanobots swarm through the target's biological or mechanical systems.</p><hr /><p><strong>Heightened (+1)</strong> The damage increases by 2d6.</p>"
                },
                "duration": {
                    "sustained": false,
                    "value": ""
                },
                "heightening": {
                    "area": 0,
                    "damage": {
                        "Xdnfrdvjfv7q0CPF": "2d6"
                    },
                    "interval": 1,
                    "type": "interval"
                },
                "level": {
                    "value": 2
                },
                "location": {
                    "heightenedLevel": 2,
                    "value": "Tz40XsThj2Ou0XlF"
                },
                "publication": {
                    "license": "ORC",
                    "remaster": true,
                    "title": "Starfinder Player Core"
                },
                "range": {
                    "value": "touch"
                },
                "requirements": "",
                "rules": [],
                "slug": "inject-nanobots",
                "target": {
                    "value": "1 creature"
                },
                "time": {
                    "value": "2"
                },
                "traits": {
                    "rarity": "common",
                    "traditions": [
                        "arcane"
                    ],
                    "value": [
                        "acid",
                        "attack",
                        "concentrate",
                        "manipulate"
                    ]
                }
            },
            "type": "spell"
        },
        {
            "_id": "VBngL7xt8CpyVScp",
            "folder": "KGETkFaB5r8FyUND",
            "img": "systems/sf2e/icons/abilities/purple-tentacle.webp",
            "name": "Instant Virus",
            "sort": 300000,
            "system": {
                "area": null,
                "cost": {
                    "value": ""
                },
                "counteraction": false,
                "damage": {},
                "defense": {
                    "save": {
                        "basic": false,
                        "statistic": "fortitude"
                    }
                },
                "description": {
                    "value": "<p>Your touch installs a dangerous self-replicating virus that disrupts a technological creature's programming. The target must attempt a Fortitude save.</p><hr /><p><strong>Critical Success</strong> The target is unaffected.</p>\n<p><strong>Success</strong> The target is @UUID[Compendium.sf2e.conditions.Item.Glitching]{Glitching 1}.</p>\n<p><strong>Failure</strong> The target is glitching 1 and @UUID[Compendium.sf2e.conditions.Item.Stunned]{Stunned 1}.</p>\n<p><strong>Critical Failure</strong> The target is @UUID[Compendium.sf2e.conditions.Item.Glitching]{Glitching 2} and @UUID[Compendium.sf2e.conditions.Item.Stunned]{Stunned 2}.</p>"
                },
                "duration": {
                    "sustained": false,
                    "value": ""
                },
                "level": {
                    "value": 2
                },
                "location": {
                    "heightenedLevel": 2,
                    "value": "Tz40XsThj2Ou0XlF"
                },
                "publication": {
                    "license": "ORC",
                    "remaster": true,
                    "title": "Starfinder Player Core"
                },
                "range": {
                    "value": "touch"
                },
                "requirements": "",
                "rules": [],
                "slug": "instant-virus",
                "target": {
                    "value": "1 creature with the tech trait"
                },
                "time": {
                    "value": "2"
                },
                "traits": {
                    "rarity": "common",
                    "traditions": [
                        "arcane"
                    ],
                    "value": [
                        "concentrate",
                        "manipulate"
                    ]
                }
            },
            "type": "spell"
        },
        {
            "_id": "uwOvgBoBhOc2V9Pl",
            "folder": "D7UVaOiB40wTR6kv",
            "img": "icons/magic/lightning/bolt-strike-forked-blue.webp",
            "name": "Electric Arc",
            "sort": 400000,
            "system": {
                "area": null,
                "cost": {
                    "value": ""
                },
                "counteraction": false,
                "damage": {
                    "0": {
                        "applyMod": false,
                        "category": null,
                        "formula": "2d4",
                        "kinds": [
                            "damage"
                        ],
                        "materials": [],
                        "type": "electricity"
                    }
                },
                "defense": {
                    "save": {
                        "basic": true,
                        "statistic": "reflex"
                    }
                },
                "description": {
                    "value": "<p>An arc of lightning leaps from one target to another. Each target takes 2d4 electricity damage with a basic Reflex save.</p>\n<hr />\n<p><strong>Heightened (+1)</strong> The damage increases by 1d4.</p>"
                },
                "duration": {
                    "sustained": false,
                    "value": ""
                },
                "heightening": {
                    "damage": {
                        "0": "1d4"
                    },
                    "interval": 1,
                    "type": "interval"
                },
                "level": {
                    "value": 1
                },
                "location": {
                    "value": "Tz40XsThj2Ou0XlF"
                },
                "publication": {
                    "license": "ORC",
                    "remaster": true,
                    "title": "Pathfinder Player Core"
                },
                "range": {
                    "value": "30 feet"
                },
                "requirements": "",
                "rules": [],
                "slug": "electric-arc",
                "target": {
                    "value": "1 or 2 creatures"
                },
                "time": {
                    "value": "2"
                },
                "traits": {
                    "rarity": "common",
                    "traditions": [
                        "arcane",
                        "primal"
                    ],
                    "value": [
                        "cantrip",
                        "concentrate",
                        "electricity",
                        "manipulate"
                    ]
                }
            },
            "type": "spell"
        },
        {
            "_id": "WaI6Mk6qebrvN3H6",
            "folder": "T8AzYUgNIAgTJ9Iz",
            "img": "systems/sf2e/icons/spells/mending.webp",
            "name": "Mending",
            "sort": 500000,
            "system": {
                "area": null,
                "cost": {
                    "value": ""
                },
                "counteraction": false,
                "damage": {},
                "defense": null,
                "description": {
                    "value": "<p>You repair the target item. You restore 5 Hit Points per spell rank to the target, potentially removing the @UUID[Compendium.sf2e.conditions.Item.Broken] condition if this repairs it past the item's Broken Threshold. You can't replace lost pieces or repair an object that's been completely destroyed.</p>\n<hr />\n<p><strong>Heightened (2nd)</strong> You can target a non-magical object of 1 Bulk or less.</p>\n<p><strong>Heightened (3rd)</strong> You can target a non-magical object of 2 Bulk or less, or a magical object of 1 Bulk or less.</p>"
                },
                "duration": {
                    "sustained": false,
                    "value": ""
                },
                "heightening": {
                    "levels": {
                        "2": {
                            "target": {
                                "value": "non-magical object of 1 Bulk or less"
                            }
                        },
                        "3": {
                            "target": {
                                "value": "non-magical object of 2 Bulk or less, or a magical object of 1 Bulk or less"
                            }
                        }
                    },
                    "type": "fixed"
                },
                "level": {
                    "value": 1
                },
                "location": {
                    "heightenedLevel": 1,
                    "value": "Tz40XsThj2Ou0XlF"
                },
                "publication": {
                    "license": "ORC",
                    "remaster": true,
                    "title": "Pathfinder Player Core"
                },
                "range": {
                    "value": "touch"
                },
                "requirements": "",
                "rules": [],
                "slug": "mending",
                "target": {
                    "value": "non-magical object of light Bulk or less"
                },
                "time": {
                    "value": "10 minutes"
                },
                "traits": {
                    "rarity": "common",
                    "traditions": [
                        "arcane",
                        "divine",
                        "occult",
                        "primal"
                    ],
                    "value": [
                        "concentrate",
                        "manipulate"
                    ]
                }
            },
            "type": "spell"
        },
        {
            "_id": "ia2Oc4Pi2YWIyrGo",
            "folder": "PUfxgisPd7TTDluV",
            "img": "systems/sf2e/icons/abilities/blue-battery-gauge.webp",
            "name": "Recharge Weapon",
            "sort": 600000,
            "system": {
                "area": null,
                "cost": {
                    "value": ""
                },
                "counteraction": false,
                "damage": {},
                "defense": null,
                "description": {
                    "value": "<p>You touch a weapon with no remaining ammunition and recharge it with magical energy. The target gains ammunition or charges equal to its expend until the end of your next turn, allowing anyone holding the target to make one Strike with the weapon. This spell only recharges weapons that use ammunition with a cost of 10 credits or less.</p><hr /><p><strong>Heightened (3rd)</strong> The target gains ammunition or charges equal to double its expend.</p>\n<p><strong>Heightened (6th)</strong> The target gains ammunition or charges equal to triple its expend.</p>\n<p><strong>Heightened (9th)</strong> The target gains ammunition or charges equal to quadruple its expend.</p>"
                },
                "duration": {
                    "sustained": false,
                    "value": ""
                },
                "level": {
                    "value": 1
                },
                "location": {
                    "value": "Tz40XsThj2Ou0XlF"
                },
                "publication": {
                    "license": "ORC",
                    "remaster": true,
                    "title": "Starfinder Player Core"
                },
                "range": {
                    "value": "touch"
                },
                "requirements": "",
                "rules": [],
                "slug": "recharge-weapon",
                "target": {
                    "value": "1 weapon with capacity"
                },
                "time": {
                    "value": "1"
                },
                "traits": {
                    "rarity": "common",
                    "traditions": [
                        "arcane",
                        "occult"
                    ],
                    "value": [
                        "cantrip",
                        "concentrate",
                        "manipulate"
                    ]
                }
            },
            "type": "spell"
        },
        {
            "_id": "Xz3R3Ciw6v9xju1i",
            "folder": "9xujKNVgcczpuL4g",
            "img": "icons/skills/movement/figure-running-gray.webp",
            "name": "Stumble",
            "sort": 700000,
            "system": {
                "area": null,
                "cost": {
                    "value": ""
                },
                "counteraction": false,
                "damage": {},
                "defense": {
                    "save": {
                        "basic": false,
                        "statistic": "reflex"
                    }
                },
                "description": {
                    "value": "<p>A burst of microgravity causes a tremor around the target, pulling it toward the ground. The target must attempt a Reflex save.</p><hr /><p><strong>Failure</strong> The target becomes @UUID[Compendium.sf2e.conditions.Item.Off-Guard] for 1 round. If the target was flying, swimming, or floating, it falls 10 feet downward.</p>\n<p><strong>Critical Failure</strong> The target falls @UUID[Compendium.sf2e.conditions.Item.Prone]. If the target was flying, swimming, or floating, it falls 20 feet downward.</p><hr /><p><strong>Heightened (+1)</strong> If the target falls, it falls an additional 5 feet on a failure and 10 feet on a critical failure.</p>"
                },
                "duration": {
                    "sustained": false,
                    "value": ""
                },
                "level": {
                    "value": 1
                },
                "location": {
                    "value": "Tz40XsThj2Ou0XlF"
                },
                "publication": {
                    "license": "ORC",
                    "remaster": true,
                    "title": "Starfinder Player Core"
                },
                "range": {
                    "value": "100 feet"
                },
                "requirements": "",
                "rules": [],
                "slug": "stumble",
                "target": {
                    "value": "1 creature"
                },
                "time": {
                    "value": "2"
                },
                "traits": {
                    "rarity": "common",
                    "traditions": [
                        "arcane",
                        "primal"
                    ],
                    "value": [
                        "cantrip",
                        "concentrate",
                        "manipulate"
                    ]
                }
            },
            "type": "spell"
        },
        {
            "_id": "sx2lQc6EiatbAFeE",
            "folder": "PUfxgisPd7TTDluV",
            "img": "systems/sf2e/icons/abilities/blue-battery.webp",
            "name": "Supercharge Weapon",
            "sort": 800000,
            "system": {
                "area": null,
                "cost": {
                    "value": ""
                },
                "counteraction": false,
                "damage": {},
                "defense": null,
                "description": {
                    "value": "<p>You draw in and condense ambient magical energy from around you to power up a weapon. The next Strike made using that weapon is supercharged. That Strike deals an additional 1d6 damage of the same type as the weapon's normal damage.</p>\n<p>@UUID[Compendium.sf2e.spell-effects.Item.Spell Effect: Supercharge Weapon]</p><hr /><p><strong>Heightened (+2)</strong> The extra damage increases by 1d6.</p>"
                },
                "duration": {
                    "sustained": false,
                    "value": "1 minute or until discharged"
                },
                "level": {
                    "value": 1
                },
                "location": {
                    "heightenedLevel": 1,
                    "value": "Tz40XsThj2Ou0XlF"
                },
                "publication": {
                    "license": "ORC",
                    "remaster": true,
                    "title": "Starfinder Player Core"
                },
                "range": {
                    "value": "30 feet"
                },
                "requirements": "",
                "rules": [],
                "slug": "supercharge-weapon",
                "target": {
                    "value": "1 weapon held by you or a willing ally"
                },
                "time": {
                    "value": "2"
                },
                "traits": {
                    "rarity": "common",
                    "traditions": [
                        "arcane"
                    ],
                    "value": [
                        "concentrate",
                        "manipulate"
                    ]
                }
            },
            "type": "spell"
        },
        {
            "_id": "bz9uVdNS4TwyHLqO",
            "folder": "V89RPpe7fyCFC6NS",
            "img": "icons/weapons/guns/rifle-fluted.webp",
            "name": "Arc Rifle",
            "sort": 900000,
            "system": {
                "ammo": {
                    "baseType": "battery",
                    "builtIn": false,
                    "capacity": 1
                },
                "baseItem": "arc-rifle",
                "bonus": {
                    "value": 0
                },
                "bonusDamage": {
                    "value": 0
                },
                "bulk": {
                    "value": 2
                },
                "category": "simple",
                "containerId": null,
                "damage": {
                    "damageType": "electricity",
                    "dice": 1,
                    "die": "d6"
                },
                "description": {
                    "value": "<p><strong>Upgrades:</strong> 1</p><hr /><p>This rifle's oversized body contains a larger version of an arc pistol capacitor, with a short barrel and polycarbon stock designed to insulate the wielder from high voltage. The arc rifle's larger capacitor allows it to produce a charge with enough power to subdue a rampaging renkroda.</p>"
                },
                "equipped": {
                    "carryType": "worn",
                    "handsHeld": 0,
                    "invested": null
                },
                "expend": 2,
                "grade": "tactical",
                "group": "shock",
                "hardness": 0,
                "hp": {
                    "max": 0,
                    "value": 0
                },
                "level": {
                    "value": 0
                },
                "material": {
                    "grade": null,
                    "type": null
                },
                "price": {
                    "value": {
                        "sp": 50
                    }
                },
                "publication": {
                    "license": "ORC",
                    "remaster": true,
                    "title": "Starfinder Player Core"
                },
                "quantity": 1,
                "range": 50,
                "reload": {
                    "value": "1"
                },
                "rules": [],
                "runes": {
                    "potency": 0,
                    "property": [],
                    "striking": 0
                },
                "size": "tiny",
                "slug": "arc-rifle",
                "splashDamage": {
                    "value": 0
                },
                "traits": {
                    "rarity": "common",
                    "value": [
                        "arc",
                        "tech"
                    ]
                },
                "usage": {
                    "value": "held-in-two-hands"
                }
            },
            "type": "weapon"
        },
        {
            "_id": "eLH2GxmU2pxjR7JM",
            "folder": "F6h7fO0Z7cgQBVRD",
            "img": "systems/sf2e/icons/equipment/other/green-battery.webp",
            "name": "Battery (Commercial)",
            "sort": 1000000,
            "system": {
                "baseItem": "battery",
                "bulk": {
                    "value": 0
                },
                "containerId": null,
                "craftableAs": null,
                "description": {
                    "value": ""
                },
                "equipped": {
                    "carryType": "worn"
                },
                "hardness": 0,
                "hp": {
                    "max": 0,
                    "value": 0
                },
                "level": {
                    "value": 0
                },
                "material": {
                    "grade": null,
                    "type": null
                },
                "price": {
                    "per": 1,
                    "value": {
                        "sp": 10
                    }
                },
                "publication": {
                    "license": "ORC",
                    "remaster": true,
                    "title": "Starfinder Player Core"
                },
                "quantity": 1,
                "rules": [],
                "size": "tiny",
                "slug": "battery-commercial",
                "traits": {
                    "rarity": "common",
                    "value": []
                },
                "uses": {
                    "autoDestroy": true,
                    "max": 10,
                    "value": 10
                }
            },
            "type": "ammo"
        },
        {
            "_id": "Ndb1dZyT1zR0hx7Y",
            "flags": {
                "sf2e": {
                    "linkedWeapon": "bz9uVdNS4TwyHLqO"
                }
            },
            "img": "systems/sf2e/icons/default-icons/melee.svg",
            "name": "Arc Rifle",
            "sort": 1100000,
            "system": {
                "action": "strike",
                "area": null,
                "attackEffects": {
                    "value": []
                },
                "bonus": {
                    "value": 9
                },
                "damageRolls": {
                    "T6qCM1tbVhv5Cj7B": {
                        "damage": "1d6",
                        "damageType": "electricity"
                    }
                },
                "description": {
                    "value": ""
                },
                "publication": {
                    "license": "OGL",
                    "remaster": false,
                    "title": ""
                },
                "range": {
                    "increment": 50,
                    "max": null
                },
                "rules": [],
                "slug": "arc-rifle",
                "traits": {
                    "value": [
                        "reload-1",
                        "tech",
                        "tracking-1"
                    ]
                }
            },
            "type": "melee"
        },
        {
            "_id": "yvgyJFhxwZ82Bbfh",
            "img": "systems/sf2e/icons/default-icons/melee.svg",
            "name": "Tail",
            "sort": 1200000,
            "system": {
                "action": "strike",
                "area": null,
                "attackEffects": {
                    "value": []
                },
                "bonus": {
                    "value": 8
                },
                "damageRolls": {
                    "hDH7GvdVrtDX6CIu": {
                        "damage": "1d6",
                        "damageType": "slashing"
                    }
                },
                "description": {
                    "value": ""
                },
                "publication": {
                    "license": "OGL",
                    "remaster": false,
                    "title": ""
                },
                "range": null,
                "rules": [],
                "slug": null,
                "traits": {
                    "value": [
                        "agile",
                        "finesse"
                    ]
                }
            },
            "type": "melee"
        },
        {
            "_id": "gFejGfzEnqTKrsFw",
            "img": "systems/sf2e/icons/actions/Passive.webp",
            "name": "Scoring",
            "sort": 1300000,
            "system": {
                "actionType": {
                    "value": "passive"
                },
                "actions": {
                    "value": null
                },
                "category": "offensive",
                "description": {
                    "value": "<p>When the tool rat's tail Strike deals damage to an object or creature with the tech trait, the tail also gains the following traits until the beginning of the scrap rat's next turn: deadly d4, hampering, and razing.</p>\n<p>@UUID[Compendium.sf2e.bestiary-effects.Item.Effect: Scoring]</p>"
                },
                "publication": {
                    "license": "OGL",
                    "remaster": false,
                    "title": ""
                },
                "rules": [],
                "slug": null,
                "traits": {
                    "value": []
                }
            },
            "type": "action"
        },
        {
            "_id": "keWkSUziBg60dAUX",
            "img": "systems/sf2e/icons/actions/Passive.webp",
            "name": "Upscaled Recycling",
            "sort": 1400000,
            "system": {
                "actionType": {
                    "value": "passive"
                },
                "actions": {
                    "value": null
                },
                "category": "offensive",
                "description": {
                    "value": "<p>Over the course of 1 hour of uninterrupted work, a tool rat can assemble a simple tactical weapon of any type, up to 2nd level, including a single @UUID[Compendium.sf2e.equipment.Item.Battery (Commercial)]{commercial battery} or a full magazine of projectile ammunition. using nothing but junk. It falls apart and becomes unusable junk after 10 minutes.</p>"
                },
                "publication": {
                    "license": "OGL",
                    "remaster": false,
                    "title": ""
                },
                "rules": [],
                "slug": null,
                "traits": {
                    "value": []
                }
            },
            "type": "action"
        }
    ],
    "name": "Tool Rat",
    "system": {
        "abilities": {
            "cha": {
                "mod": 0
            },
            "con": {
                "mod": 0
            },
            "dex": {
                "mod": 0
            },
            "int": {
                "mod": 0
            },
            "str": {
                "mod": 0
            },
            "wis": {
                "mod": 0
            }
        },
        "attributes": {
            "ac": {
                "details": "",
                "value": 10
            },
            "allSaves": {
                "value": ""
            },
            "hp": {
                "details": "",
                "max": 10,
                "temp": 0,
                "value": 10
            },
            "speed": {
                "otherSpeeds": [
                    {
                        "type": "climb",
                        "value": 10
                    }
                ],
                "value": 25
            }
        },
        "details": {
            "blurb": "",
            "languages": {
                "details": "",
                "value": []
            },
            "level": {
                "value": 2
            },
            "privateNotes": "",
            "publicNotes": "<p>The tool rat resembles an infant of their kind, but closer study reveals coppery whiskers akin to a dwarven beard and eyebrows. Intuitive spellcraft helps them turn junkyards into minefields for the unwary</p><hr /><p>When pileups of metal garbage begin to conquer the wilderness, rodents conquer the garbage. Scrap rats adapt to every civilization that disposes their ruined gadgets and industrial debris, all of which the rats recycle and reuse to potentially deadly effect. While not especially intelligent, they have an innate knack for crafting.</p>",
            "publication": {
                "license": "ORC",
                "remaster": true,
                "title": "Starfinder Alien Core"
            }
        },
        "initiative": {
            "statistic": "perception"
        },
        "perception": {
            "details": "",
            "mod": 0,
            "senses": []
        },
        "resources": {},
        "saves": {
            "fortitude": {
                "saveDetail": "",
                "value": 0
            },
            "reflex": {
                "saveDetail": "",
                "value": 0
            },
            "will": {
                "saveDetail": "",
                "value": 0
            }
        },
        "skills": {},
        "traits": {
            "rarity": "common",
            "size": {
                "value": "tiny"
            },
            "value": [
                "beast"
            ]
        }
    },
    "type": "npc"
}
