{
    "_id": "4DAzA9ssned4f5SP",
    "img": "systems/sf2e/icons/default-icons/hazard.svg",
    "items": [
        {
            "_id": "jypNQd23yJERP7wY",
            "img": "systems/sf2e/icons/actions/Reaction.webp",
            "name": "Tentacle Slam",
            "sort": 0,
            "system": {
                "actionType": {
                    "value": "reaction"
                },
                "actions": {
                    "value": null
                },
                "category": "offensive",
                "description": {
                    "value": "<p><strong>Trigger</strong> A creature takes a hostile action against the kyokor, produces a visible area effect, or flies within 120 feet of the kyokor</p><hr /><p><strong>Effect</strong> The kyokor deals @Damage[(6d10+28)[bludgeoning]|options:area-damage] damage in a @Template[type:line|distance:120], and each creature in the area must attempt a @Check[reflex|dc:40] save.</p><hr /><p><strong>Critical Success</strong> The creature is unaffected.</p>\n<p><strong>Success</strong> The creature takes half damage and is pushed 20 feet away. If flying, it descends 20 feet.</p>\n<p><strong>Failure</strong> The creature takes full damage, is pushed 40 feet, and descends 60 feet (if flying) or is knocked @UUID[Compendium.sf2e.conditions.Item.Prone].</p>\n<p><strong>Critical Failure</strong> The creature takes double damage, is pushed 60 feet away, descends 120 feet (if flying) or is knocked prone, and is @UUID[Compendium.sf2e.conditions.Item.Stunned]{Stunned 2}.</p>"
                },
                "publication": {
                    "license": "OGL",
                    "remaster": false,
                    "title": ""
                },
                "rules": [],
                "slug": null,
                "traits": {
                    "value": []
                }
            },
            "type": "action"
        }
    ],
    "name": "Writhing Tentacles",
    "system": {
        "attributes": {
            "ac": {
                "value": null
            },
            "emitsSound": "encounter",
            "hardness": 0,
            "hp": {
                "details": "",
                "max": 0,
                "temp": 0,
                "value": 0
            },
            "immunities": [],
            "resistances": [],
            "stealth": {
                "details": "",
                "value": 0
            },
            "weaknesses": []
        },
        "details": {
            "description": "<p>The kyokor's tentacles snake out, causing devastation.</p><hr /><p>When a kyokor passes by or through a settlement—or even attacks!—it leaves a trail of destruction that can be represented by the following hazards.</p><hr /><p>Terrifying, skyscraper-sized beasts roam the wastelands of Daimalko. Called colossi by the population, these monsters erupted from deep within the earth to stomp cities into dust, decimating the population and destroying every surface civilization on the planet in a terrifying Awakening. Kyokors are among the most dreaded colossi. There's no hope of defeating one without a valko—a war machine created by Daimalko's stubborn survivors to fight the colossi.</p>",
            "disable": "<p>@Check[arcana|dc:45] (legendary), @Check[occultism|dc:45] (legendary), or @Check[performance|dc:45] (legendary) to soothe or divert the kyokor's attention; using a guardian orb (see the sidebar on this page) to command the kyokor ends the hazard</p>",
            "isComplex": false,
            "level": {
                "value": 18
            },
            "publication": {
                "license": "ORC",
                "remaster": true,
                "title": "Starfinder Alien Core"
            },
            "reset": "<p>The kyokor's tentacles can't writhe again for [[/gmr 1d4 #Recharge writhe]]{1d4 rounds}.</p>",
            "routine": ""
        },
        "saves": {
            "fortitude": {
                "value": 0
            },
            "reflex": {
                "value": 0
            },
            "will": {
                "value": 0
            }
        },
        "traits": {
            "rarity": "common",
            "size": {
                "value": "lg"
            },
            "value": [
                "kaiju",
                "environmental"
            ]
        }
    },
    "type": "hazard"
}
