{
    "_id": "AvfH1TgQFIOkHp5n",
    "folder": "6LQHPVu96U3qBoLm",
    "img": "systems/sf2e/icons/default-icons/feats-sf2e.webp",
    "name": "Tech Familiarity",
    "system": {
        "actionType": {
            "value": "passive"
        },
        "actions": {
            "value": null
        },
        "category": "ancestry",
        "description": {
            "value": "<p>You have an intuitive understanding of computers, machines, and other technological devices. You become trained in Computers and Crafting. If you would automatically become trained in one of those skills (from your background or class, for example), you instead become trained in a skill of your choice.</p>"
        },
        "level": {
            "value": 1
        },
        "prerequisites": {
            "value": []
        },
        "publication": {
            "license": "ORC",
            "remaster": true,
            "title": "Starfinder Player Core"
        },
        "rules": [
            {
                "key": "ActiveEffectLike",
                "mode": "upgrade",
                "path": "system.skills.computers.rank",
                "value": 1
            },
            {
                "key": "ActiveEffectLike",
                "mode": "upgrade",
                "path": "system.skills.crafting.rank",
                "value": 1
            }
        ],
        "subfeatures": {
            "proficiencies": {},
            "senses": {},
            "suppressedFeatures": []
        },
        "traits": {
            "rarity": "common",
            "value": [
                "prismeni"
            ]
        }
    },
    "type": "feat"
}
