{
    "_id": "a180Wn9Ah604bJST",
    "folder": "jjcF0lfrc3ZIoKv1",
    "img": "icons/equipment/chest/coat-collared-red.webp",
    "name": "Swarmsuit",
    "system": {
        "acBonus": 4,
        "baseItem": "swarmsuit",
        "bulk": {
            "value": 2
        },
        "category": "medium",
        "checkPenalty": -2,
        "containerId": null,
        "description": {
            "value": "<p><strong>Upgrades:</strong> 1</p><hr /><p>Specialized nanites form a mesh suit that shifts to fit wearers with unique or transformable physiologies.</p>"
        },
        "dexCap": 1,
        "grade": "commercial",
        "group": "chain",
        "hardness": 0,
        "hp": {
            "max": 0,
            "value": 0
        },
        "level": {
            "value": 0
        },
        "material": {
            "grade": null,
            "type": null
        },
        "price": {
            "value": {
                "sp": 75
            }
        },
        "publication": {
            "license": "ORC",
            "remaster": true,
            "title": "Starfinder Player Core"
        },
        "quantity": 1,
        "rules": [],
        "runes": {
            "potency": 0,
            "property": [],
            "resilient": 0
        },
        "size": "med",
        "speedPenalty": -5,
        "strength": 3,
        "traits": {
            "rarity": "common",
            "value": [
                "flexible",
                "noisy",
                "tech"
            ]
        }
    },
    "type": "armor"
}
