{
    "_id": "sAI6yzB11LlxisD7",
    "img": "systems/pf2e/icons/equipment/adventuring-gear/grapling-bolt.webp",
    "name": "Grappling Bolt",
    "system": {
        "baseItem": "bolts",
        "bulk": {
            "value": 0.1
        },
        "containerId": null,
        "craftableAs": null,
        "description": {
            "value": "<p>This small grappling hook is designed to be tied to a rope and fired from a crossbow. When fired, it has half the normal range increment for the weapon.</p>"
        },
        "level": {
            "value": 0
        },
        "price": {
            "value": {
                "sp": 2
            }
        },
        "publication": {
            "license": "OGL",
            "remaster": false,
            "title": "Pathfinder Lost Omens Pathfinder Society Guide"
        },
        "quantity": 1,
        "rules": [],
        "size": "med",
        "traits": {
            "rarity": "uncommon",
            "value": []
        },
        "uses": {
            "autoDestroy": true,
            "max": 1,
            "value": 1
        }
    },
    "type": "ammo"
}
